django_kubernetes-1.1.0.dist-info/licenses/LICENSE
djk8s/__init__.py
djk8s/apps.py
djk8s/conf.py
djk8s/middleware.py
djk8s/probes.py
djk8s/urls.py
djk8s/version.py
djk8s/views.py
djk8s/management/__init__.py
djk8s/management/commands/__init__.py
djk8s/management/commands/ensureadmin.py
djk8s/management/commands/lockedmigrate.py
djk8s/management/commands/probe.py
djk8s/management/commands/wait4db.py
djk8s/migrations/__init__.py
django_kubernetes-1.1.0.dist-info/METADATA
django_kubernetes-1.1.0.dist-info/WHEEL
django_kubernetes-1.1.0.dist-info/top_level.txt
django_kubernetes-1.1.0.dist-info/RECORD
